{
  "DataList": [
    {
      "EventContentId": 801,
      "CategoryType": "EventContent_0",
      "LocalizeCode": 1848737157,
      "CostParcelType": "Item",
      "CostParcelId": 80001,
      "IsRefresh": false,
      "AutoRefreshCoolTime": 0,
      "RefreshAbleCount": 0,
      "GoodsId": [],
      "OpenPeriodFrom": null,
      "OpenPeriodTo": null
    },
    {
      "EventContentId": 801,
      "CategoryType": "EventContent_1",
      "LocalizeCode": 3452599573,
      "CostParcelType": "Item",
      "CostParcelId": 80002,
      "IsRefresh": false,
      "AutoRefreshCoolTime": 0,
      "RefreshAbleCount": 0,
      "GoodsId": [],
      "OpenPeriodFrom": null,
      "OpenPeriodTo": null
    },
    {
      "EventContentId": 801,
      "CategoryType": "EventContent_2",
      "LocalizeCode": 3837426357,
      "CostParcelType": "Item",
      "CostParcelId": 80003,
      "IsRefresh": false,
      "AutoRefreshCoolTime": 0,
      "RefreshAbleCount": 0,
      "GoodsId": [],
      "OpenPeriodFrom": null,
      "OpenPeriodTo": null
    },
    {
      "EventContentId": 802,
      "CategoryType": "EventContent_0",
      "LocalizeCode": 357822895,
      "CostParcelType": "Item",
      "CostParcelId": 80011,
      "IsRefresh": false,
      "AutoRefreshCoolTime": 0,
      "RefreshAbleCount": 0,
      "GoodsId": [],
      "OpenPeriodFrom": null,
      "OpenPeriodTo": null
    },
    {
      "EventContentId": 802,
      "CategoryType": "EventContent_1",
      "LocalizeCode": 357822895,
      "CostParcelType": "Item",
      "CostParcelId": 80012,
      "IsRefresh": false,
      "AutoRefreshCoolTime": 0,
      "RefreshAbleCount": 0,
      "GoodsId": [],
      "OpenPeriodFrom": null,
      "OpenPeriodTo": null
    },
    {
      "EventContentId": 802,
      "CategoryType": "EventContent_2",
      "LocalizeCode": 357822895,
      "CostParcelType": "Item",
      "CostParcelId": 80013,
      "IsRefresh": false,
      "AutoRefreshCoolTime": 0,
      "RefreshAbleCount": 0,
      "GoodsId": [],
      "OpenPeriodFrom": null,
      "OpenPeriodTo": null
    },
    {
      "EventContentId": 803,
      "CategoryType": "EventContent_0",
      "LocalizeCode": 357822895,
      "CostParcelType": "Item",
      "CostParcelId": 80021,
      "IsRefresh": false,
      "AutoRefreshCoolTime": 0,
      "RefreshAbleCount": 0,
      "GoodsId": [],
      "OpenPeriodFrom": null,
      "OpenPeriodTo": null
    },
    {
      "EventContentId": 803,
      "CategoryType": "EventContent_1",
      "LocalizeCode": 357822895,
      "CostParcelType": "Item",
      "CostParcelId": 80022,
      "IsRefresh": false,
      "AutoRefreshCoolTime": 0,
      "RefreshAbleCount": 0,
      "GoodsId": [],
      "OpenPeriodFrom": null,
      "OpenPeriodTo": null
    },
    {
      "EventContentId": 803,
      "CategoryType": "EventContent_2",
      "LocalizeCode": 357822895,
      "CostParcelType": "Item",
      "CostParcelId": 80023,
      "IsRefresh": false,
      "AutoRefreshCoolTime": 0,
      "RefreshAbleCount": 0,
      "GoodsId": [],
      "OpenPeriodFrom": null,
      "OpenPeriodTo": null
    },
    {
      "EventContentId": 803,
      "CategoryType": "EventContent_3",
      "LocalizeCode": 357822895,
      "CostParcelType": "Item",
      "CostParcelId": 80020,
      "IsRefresh": false,
      "AutoRefreshCoolTime": 0,
      "RefreshAbleCount": 0,
      "GoodsId": [],
      "OpenPeriodFrom": null,
      "OpenPeriodTo": null
    },
    {
      "EventContentId": 804,
      "CategoryType": "EventContent_0",
      "LocalizeCode": 357822895,
      "CostParcelType": "Item",
      "CostParcelId": 80031,
      "IsRefresh": false,
      "AutoRefreshCoolTime": 0,
      "RefreshAbleCount": 0,
      "GoodsId": [],
      "OpenPeriodFrom": null,
      "OpenPeriodTo": null
    },
    {
      "EventContentId": 804,
      "CategoryType": "EventContent_1",
      "LocalizeCode": 357822895,
      "CostParcelType": "Item",
      "CostParcelId": 80032,
      "IsRefresh": false,
      "AutoRefreshCoolTime": 0,
      "RefreshAbleCount": 0,
      "GoodsId": [],
      "OpenPeriodFrom": null,
      "OpenPeriodTo": null
    },
    {
      "EventContentId": 804,
      "CategoryType": "EventContent_2",
      "LocalizeCode": 357822895,
      "CostParcelType": "Item",
      "CostParcelId": 80033,
      "IsRefresh": false,
      "AutoRefreshCoolTime": 0,
      "RefreshAbleCount": 0,
      "GoodsId": [],
      "OpenPeriodFrom": null,
      "OpenPeriodTo": null
    },
    {
      "EventContentId": 805,
      "CategoryType": "EventContent_0",
      "LocalizeCode": 357822895,
      "CostParcelType": "Item",
      "CostParcelId": 80041,
      "IsRefresh": false,
      "AutoRefreshCoolTime": 0,
      "RefreshAbleCount": 0,
      "GoodsId": [],
      "OpenPeriodFrom": null,
      "OpenPeriodTo": null
    },
    {
      "EventContentId": 805,
      "CategoryType": "EventContent_1",
      "LocalizeCode": 357822895,
      "CostParcelType": "Item",
      "CostParcelId": 80042,
      "IsRefresh": false,
      "AutoRefreshCoolTime": 0,
      "RefreshAbleCount": 0,
      "GoodsId": [],
      "OpenPeriodFrom": null,
      "OpenPeriodTo": null
    },
    {
      "EventContentId": 805,
      "CategoryType": "EventContent_2",
      "LocalizeCode": 357822895,
      "CostParcelType": "Item",
      "CostParcelId": 80043,
      "IsRefresh": false,
      "AutoRefreshCoolTime": 0,
      "RefreshAbleCount": 0,
      "GoodsId": [],
      "OpenPeriodFrom": null,
      "OpenPeriodTo": null
    },
    {
      "EventContentId": 805,
      "CategoryType": "EventContent_3",
      "LocalizeCode": 357822895,
      "CostParcelType": "Item",
      "CostParcelId": 80040,
      "IsRefresh": false,
      "AutoRefreshCoolTime": 0,
      "RefreshAbleCount": 0,
      "GoodsId": [],
      "OpenPeriodFrom": null,
      "OpenPeriodTo": null
    },
    {
      "EventContentId": 806,
      "CategoryType": "EventContent_0",
      "LocalizeCode": 357822895,
      "CostParcelType": "Item",
      "CostParcelId": 80051,
      "IsRefresh": false,
      "AutoRefreshCoolTime": 0,
      "RefreshAbleCount": 0,
      "GoodsId": [],
      "OpenPeriodFrom": null,
      "OpenPeriodTo": null
    },
    {
      "EventContentId": 806,
      "CategoryType": "EventContent_1",
      "LocalizeCode": 357822895,
      "CostParcelType": "Item",
      "CostParcelId": 80052,
      "IsRefresh": false,
      "AutoRefreshCoolTime": 0,
      "RefreshAbleCount": 0,
      "GoodsId": [],
      "OpenPeriodFrom": null,
      "OpenPeriodTo": null
    },
    {
      "EventContentId": 806,
      "CategoryType": "EventContent_2",
      "LocalizeCode": 357822895,
      "CostParcelType": "Item",
      "CostParcelId": 80053,
      "IsRefresh": false,
      "AutoRefreshCoolTime": 0,
      "RefreshAbleCount": 0,
      "GoodsId": [],
      "OpenPeriodFrom": null,
      "OpenPeriodTo": null
    },
    {
      "EventContentId": 808,
      "CategoryType": "EventContent_0",
      "LocalizeCode": 357822895,
      "CostParcelType": "Item",
      "CostParcelId": 80061,
      "IsRefresh": false,
      "AutoRefreshCoolTime": 0,
      "RefreshAbleCount": 0,
      "GoodsId": [],
      "OpenPeriodFrom": null,
      "OpenPeriodTo": null
    },
    {
      "EventContentId": 808,
      "CategoryType": "EventContent_1",
      "LocalizeCode": 357822895,
      "CostParcelType": "Item",
      "CostParcelId": 80062,
      "IsRefresh": false,
      "AutoRefreshCoolTime": 0,
      "RefreshAbleCount": 0,
      "GoodsId": [],
      "OpenPeriodFrom": null,
      "OpenPeriodTo": null
    },
    {
      "EventContentId": 808,
      "CategoryType": "EventContent_2",
      "LocalizeCode": 357822895,
      "CostParcelType": "Item",
      "CostParcelId": 80063,
      "IsRefresh": false,
      "AutoRefreshCoolTime": 0,
      "RefreshAbleCount": 0,
      "GoodsId": [],
      "OpenPeriodFrom": null,
      "OpenPeriodTo": null
    },
    {
      "EventContentId": 809,
      "CategoryType": "EventContent_0",
      "LocalizeCode": 357822895,
      "CostParcelType": "Item",
      "CostParcelId": 80071,
      "IsRefresh": false,
      "AutoRefreshCoolTime": 0,
      "RefreshAbleCount": 0,
      "GoodsId": [],
      "OpenPeriodFrom": null,
      "OpenPeriodTo": null
    },
    {
      "EventContentId": 809,
      "CategoryType": "EventContent_1",
      "LocalizeCode": 357822895,
      "CostParcelType": "Item",
      "CostParcelId": 80072,
      "IsRefresh": false,
      "AutoRefreshCoolTime": 0,
      "RefreshAbleCount": 0,
      "GoodsId": [],
      "OpenPeriodFrom": null,
      "OpenPeriodTo": null
    },
    {
      "EventContentId": 10801,
      "CategoryType": "EventContent_0",
      "LocalizeCode": 357822895,
      "CostParcelType": "Item",
      "CostParcelId": 85001,
      "IsRefresh": false,
      "AutoRefreshCoolTime": 0,
      "RefreshAbleCount": 0,
      "GoodsId": [],
      "OpenPeriodFrom": null,
      "OpenPeriodTo": null
    },
    {
      "EventContentId": 10801,
      "CategoryType": "EventContent_1",
      "LocalizeCode": 357822895,
      "CostParcelType": "Item",
      "CostParcelId": 85002,
      "IsRefresh": false,
      "AutoRefreshCoolTime": 0,
      "RefreshAbleCount": 0,
      "GoodsId": [],
      "OpenPeriodFrom": null,
      "OpenPeriodTo": null
    },
    {
      "EventContentId": 10801,
      "CategoryType": "EventContent_2",
      "LocalizeCode": 357822895,
      "CostParcelType": "Item",
      "CostParcelId": 85003,
      "IsRefresh": false,
      "AutoRefreshCoolTime": 0,
      "RefreshAbleCount": 0,
      "GoodsId": [],
      "OpenPeriodFrom": null,
      "OpenPeriodTo": null
    },
    {
      "EventContentId": 10801,
      "CategoryType": "EventContent_3",
      "LocalizeCode": 357822895,
      "CostParcelType": "Item",
      "CostParcelId": 85000,
      "IsRefresh": false,
      "AutoRefreshCoolTime": 0,
      "RefreshAbleCount": 0,
      "GoodsId": [],
      "OpenPeriodFrom": null,
      "OpenPeriodTo": null
    }
  ]
}
