{
  "DataList": [
    {
      "OpenConditionContentType": "Campaign",
      "LockUI": [
        "UIStageSelect",
        "UICampaign"
      ],
      "ShortcutPopupPriority": 1,
      "ShortcutUIName": [
        "UILobby",
        "UIWork"
      ],
      "Scene": "Lobby",
      "HideWhenLocked": false,
      "AccountLevel": 1,
      "CampaignStageId": 0,
      "MultipleConditionCheckType": "And",
      "OpenDayOfWeek": "All",
      "OpenHour": 0,
      "CloseDayOfWeek": "All",
      "CloseHour": 24
    },
    {
      "OpenConditionContentType": "Echelon",
      "LockUI": [
        "UIFormation"
      ],
      "ShortcutPopupPriority": 2,
      "ShortcutUIName": [
        "UILobby"
      ],
      "Scene": "Lobby",
      "HideWhenLocked": false,
      "AccountLevel": 1,
      "CampaignStageId": 0,
      "MultipleConditionCheckType": "And",
      "OpenDayOfWeek": "All",
      "OpenHour": 0,
      "CloseDayOfWeek": "All",
      "CloseHour": 24
    },
    {
      "OpenConditionContentType": "School_Obsolete",
      "LockUI": [],
      "ShortcutPopupPriority": 0,
      "ShortcutUIName": [
        "UILobby"
      ],
      "Scene": "Lobby",
      "HideWhenLocked": false,
      "AccountLevel": 1,
      "CampaignStageId": 0,
      "MultipleConditionCheckType": "And",
      "OpenDayOfWeek": "All",
      "OpenHour": 0,
      "CloseDayOfWeek": "All",
      "CloseHour": 24
    },
    {
      "OpenConditionContentType": "Character",
      "LockUI": [
        "UICharacterCollection"
      ],
      "ShortcutPopupPriority": 3,
      "ShortcutUIName": [
        "UILobby"
      ],
      "Scene": "Lobby",
      "HideWhenLocked": false,
      "AccountLevel": 1,
      "CampaignStageId": 0,
      "MultipleConditionCheckType": "And",
      "OpenDayOfWeek": "All",
      "OpenHour": 0,
      "CloseDayOfWeek": "All",
      "CloseHour": 24
    },
    {
      "OpenConditionContentType": "Warehouse_Obsolete",
      "LockUI": [
        "UIEquipmentInventory",
        "UINonEquipmentInventory"
      ],
      "ShortcutPopupPriority": 0,
      "ShortcutUIName": [
        "UILobby"
      ],
      "Scene": "Lobby",
      "HideWhenLocked": false,
      "AccountLevel": 1,
      "CampaignStageId": 0,
      "MultipleConditionCheckType": "And",
      "OpenDayOfWeek": "All",
      "OpenHour": 0,
      "CloseDayOfWeek": "All",
      "CloseHour": 24
    },
    {
      "OpenConditionContentType": "Shop",
      "LockUI": [
        "UIShop"
      ],
      "ShortcutPopupPriority": 4,
      "ShortcutUIName": [
        "UILobby"
      ],
      "Scene": "Lobby",
      "HideWhenLocked": false,
      "AccountLevel": 1,
      "CampaignStageId": 0,
      "MultipleConditionCheckType": "And",
      "OpenDayOfWeek": "All",
      "OpenHour": 0,
      "CloseDayOfWeek": "All",
      "CloseHour": 24
    },
    {
      "OpenConditionContentType": "Gacha",
      "LockUI": [
        "UIGacha"
      ],
      "ShortcutPopupPriority": 5,
      "ShortcutUIName": [
        "UILobby"
      ],
      "Scene": "Lobby",
      "HideWhenLocked": false,
      "AccountLevel": 1,
      "CampaignStageId": 0,
      "MultipleConditionCheckType": "And",
      "OpenDayOfWeek": "All",
      "OpenHour": 0,
      "CloseDayOfWeek": "All",
      "CloseHour": 24
    },
    {
      "OpenConditionContentType": "LobbyIllust",
      "LockUI": [
        "UILobbyBgPopup"
      ],
      "ShortcutPopupPriority": 6,
      "ShortcutUIName": [
        "UILobby"
      ],
      "Scene": "Lobby",
      "HideWhenLocked": false,
      "AccountLevel": 1,
      "CampaignStageId": 0,
      "MultipleConditionCheckType": "And",
      "OpenDayOfWeek": "All",
      "OpenHour": 0,
      "CloseDayOfWeek": "All",
      "CloseHour": 24
    },
    {
      "OpenConditionContentType": "Raid",
      "LockUI": [
        "UIRaidLobby_New"
      ],
      "ShortcutPopupPriority": 7,
      "ShortcutUIName": [
        "UILobby",
        "UIWork"
      ],
      "Scene": "Lobby",
      "HideWhenLocked": false,
      "AccountLevel": 1,
      "CampaignStageId": 1031101,
      "MultipleConditionCheckType": "And",
      "OpenDayOfWeek": "All",
      "OpenHour": 0,
      "CloseDayOfWeek": "All",
      "CloseHour": 24
    },
    {
      "OpenConditionContentType": "Cafe",
      "LockUI": [
        "UICafe"
      ],
      "ShortcutPopupPriority": 8,
      "ShortcutUIName": [
        "UILobby",
        "UIAcademyLobby"
      ],
      "Scene": "Lobby",
      "HideWhenLocked": false,
      "AccountLevel": 1,
      "CampaignStageId": 0,
      "MultipleConditionCheckType": "And",
      "OpenDayOfWeek": "All",
      "OpenHour": 0,
      "CloseDayOfWeek": "All",
      "CloseHour": 24
    },
    {
      "OpenConditionContentType": "Unit_Growth_Skill",
      "LockUI": [
        "UICharacterGrowth_Skill"
      ],
      "ShortcutPopupPriority": 9,
      "ShortcutUIName": [
        "UILobby",
        "UICharacterCollection"
      ],
      "Scene": "Lobby",
      "HideWhenLocked": false,
      "AccountLevel": 1,
      "CampaignStageId": 0,
      "MultipleConditionCheckType": "And",
      "OpenDayOfWeek": "All",
      "OpenHour": 0,
      "CloseDayOfWeek": "All",
      "CloseHour": 24
    },
    {
      "OpenConditionContentType": "Unit_Growth_LevelUp",
      "LockUI": [
        "UICharacterGrowth_LvUp"
      ],
      "ShortcutPopupPriority": 10,
      "ShortcutUIName": [
        "UILobby",
        "UICharacterCollection"
      ],
      "Scene": "Lobby",
      "HideWhenLocked": false,
      "AccountLevel": 1,
      "CampaignStageId": 0,
      "MultipleConditionCheckType": "And",
      "OpenDayOfWeek": "All",
      "OpenHour": 0,
      "CloseDayOfWeek": "All",
      "CloseHour": 24
    },
    {
      "OpenConditionContentType": "Unit_Growth_Transcendence",
      "LockUI": [
        "UICharacterGrowth_Transcendence"
      ],
      "ShortcutPopupPriority": 11,
      "ShortcutUIName": [
        "UILobby",
        "UICharacterCollection"
      ],
      "Scene": "Lobby",
      "HideWhenLocked": false,
      "AccountLevel": 1,
      "CampaignStageId": 0,
      "MultipleConditionCheckType": "And",
      "OpenDayOfWeek": "All",
      "OpenHour": 0,
      "CloseDayOfWeek": "All",
      "CloseHour": 24
    },
    {
      "OpenConditionContentType": "Equipment_Growth_LevelUp",
      "LockUI": [
        "UIEquipmentGrowth_LevelUp"
      ],
      "ShortcutPopupPriority": 12,
      "ShortcutUIName": [
        "UILobby",
        "UIEquipmentInventory"
      ],
      "Scene": "Lobby",
      "HideWhenLocked": false,
      "AccountLevel": 1,
      "CampaignStageId": 0,
      "MultipleConditionCheckType": "And",
      "OpenDayOfWeek": "All",
      "OpenHour": 0,
      "CloseDayOfWeek": "All",
      "CloseHour": 24
    },
    {
      "OpenConditionContentType": "Equipment_Growth_Transcendence",
      "LockUI": [
        "UIEquipmentGrowth_Transcendence"
      ],
      "ShortcutPopupPriority": 13,
      "ShortcutUIName": [
        "UILobby",
        "UIEquipmentInventory"
      ],
      "Scene": "Lobby",
      "HideWhenLocked": false,
      "AccountLevel": 1,
      "CampaignStageId": 0,
      "MultipleConditionCheckType": "And",
      "OpenDayOfWeek": "All",
      "OpenHour": 0,
      "CloseDayOfWeek": "All",
      "CloseHour": 24
    },
    {
      "OpenConditionContentType": "WeekDungeon",
      "LockUI": [
        "UIWeekDungeonLobby"
      ],
      "ShortcutPopupPriority": 14,
      "ShortcutUIName": [
        "UILobby",
        "UIWork"
      ],
      "Scene": "Lobby",
      "HideWhenLocked": false,
      "AccountLevel": 1,
      "CampaignStageId": 1011104,
      "MultipleConditionCheckType": "And",
      "OpenDayOfWeek": "All",
      "OpenHour": 0,
      "CloseDayOfWeek": "All",
      "CloseHour": 24
    },
    {
      "OpenConditionContentType": "Arena",
      "LockUI": [
        "UIArena"
      ],
      "ShortcutPopupPriority": 15,
      "ShortcutUIName": [
        "UILobby",
        "UIWork"
      ],
      "Scene": "Lobby",
      "HideWhenLocked": false,
      "AccountLevel": 1,
      "CampaignStageId": 1041101,
      "MultipleConditionCheckType": "And",
      "OpenDayOfWeek": "All",
      "OpenHour": 0,
      "CloseDayOfWeek": "All",
      "CloseHour": 24
    },
    {
      "OpenConditionContentType": "Academy",
      "LockUI": [
        "UIAcademyLobby"
      ],
      "ShortcutPopupPriority": 16,
      "ShortcutUIName": [
        "UILobby"
      ],
      "Scene": "Lobby",
      "HideWhenLocked": false,
      "AccountLevel": 1,
      "CampaignStageId": 1021101,
      "MultipleConditionCheckType": "And",
      "OpenDayOfWeek": "All",
      "OpenHour": 0,
      "CloseDayOfWeek": "All",
      "CloseHour": 24
    },
    {
      "OpenConditionContentType": "TSA",
      "LockUI": [
        "UITSSCollection"
      ],
      "ShortcutPopupPriority": 17,
      "ShortcutUIName": [
        "UILobby"
      ],
      "Scene": "Lobby",
      "HideWhenLocked": false,
      "AccountLevel": 1,
      "CampaignStageId": 0,
      "MultipleConditionCheckType": "And",
      "OpenDayOfWeek": "All",
      "OpenHour": 0,
      "CloseDayOfWeek": "All",
      "CloseHour": 24
    },
    {
      "OpenConditionContentType": "Equip",
      "LockUI": [
        "UIEquipmentInventory"
      ],
      "ShortcutPopupPriority": 18,
      "ShortcutUIName": [
        "UILobby"
      ],
      "Scene": "Lobby",
      "HideWhenLocked": false,
      "AccountLevel": 1,
      "CampaignStageId": 0,
      "MultipleConditionCheckType": "And",
      "OpenDayOfWeek": "All",
      "OpenHour": 0,
      "CloseDayOfWeek": "All",
      "CloseHour": 24
    },
    {
      "OpenConditionContentType": "Item",
      "LockUI": [
        "UINonEquipmentInventory"
      ],
      "ShortcutPopupPriority": 19,
      "ShortcutUIName": [
        "UILobby"
      ],
      "Scene": "Lobby",
      "HideWhenLocked": false,
      "AccountLevel": 1,
      "CampaignStageId": 0,
      "MultipleConditionCheckType": "And",
      "OpenDayOfWeek": "All",
      "OpenHour": 0,
      "CloseDayOfWeek": "All",
      "CloseHour": 24
    },
    {
      "OpenConditionContentType": "Craft",
      "LockUI": [
        "UICraftDurationList"
      ],
      "ShortcutPopupPriority": 20,
      "ShortcutUIName": [
        "UILobby"
      ],
      "Scene": "Lobby",
      "HideWhenLocked": false,
      "AccountLevel": 1,
      "CampaignStageId": 0,
      "MultipleConditionCheckType": "And",
      "OpenDayOfWeek": "All",
      "OpenHour": 0,
      "CloseDayOfWeek": "All",
      "CloseHour": 24
    },
    {
      "OpenConditionContentType": "Mission",
      "LockUI": [
        "UIMission"
      ],
      "ShortcutPopupPriority": 21,
      "ShortcutUIName": [
        "UILobby"
      ],
      "Scene": "Lobby",
      "HideWhenLocked": false,
      "AccountLevel": 1,
      "CampaignStageId": 0,
      "MultipleConditionCheckType": "And",
      "OpenDayOfWeek": "All",
      "OpenHour": 0,
      "CloseDayOfWeek": "All",
      "CloseHour": 24
    }
  ]
}
