{
  "DataList": [
    {
      "Protocol": "Account_Create",
      "ContentLockType": "None",
      "OpenConditionContent": "None",
      "Currency": false,
      "Inventory": false,
      "Mail": false
    },
    {
      "Protocol": "Account_Nickname",
      "ContentLockType": "None",
      "OpenConditionContent": "None",
      "Currency": false,
      "Inventory": false,
      "Mail": false
    },
    {
      "Protocol": "Account_Auth",
      "ContentLockType": "None",
      "OpenConditionContent": "None",
      "Currency": false,
      "Inventory": false,
      "Mail": false
    },
    {
      "Protocol": "Account_CurrencySync",
      "ContentLockType": "None",
      "OpenConditionContent": "None",
      "Currency": false,
      "Inventory": false,
      "Mail": false
    },
    {
      "Protocol": "Account_SetRepresentCharacterAndComment",
      "ContentLockType": "None",
      "OpenConditionContent": "None",
      "Currency": false,
      "Inventory": false,
      "Mail": false
    },
    {
      "Protocol": "Account_GetTutorial",
      "ContentLockType": "None",
      "OpenConditionContent": "None",
      "Currency": false,
      "Inventory": false,
      "Mail": false
    },
    {
      "Protocol": "Account_SetTutorial",
      "ContentLockType": "None",
      "OpenConditionContent": "None",
      "Currency": false,
      "Inventory": false,
      "Mail": false
    },
    {
      "Protocol": "Account_PassCheck",
      "ContentLockType": "None",
      "OpenConditionContent": "None",
      "Currency": false,
      "Inventory": false,
      "Mail": false
    },
    {
      "Protocol": "Account_VerifyForYostar",
      "ContentLockType": "None",
      "OpenConditionContent": "None",
      "Currency": false,
      "Inventory": false,
      "Mail": false
    },
    {
      "Protocol": "Account_CheckYostar",
      "ContentLockType": "None",
      "OpenConditionContent": "None",
      "Currency": false,
      "Inventory": false,
      "Mail": false
    },
    {
      "Protocol": "Account_CallName",
      "ContentLockType": "None",
      "OpenConditionContent": "None",
      "Currency": false,
      "Inventory": false,
      "Mail": false
    },
    {
      "Protocol": "Account_BirthDay",
      "ContentLockType": "None",
      "OpenConditionContent": "None",
      "Currency": false,
      "Inventory": false,
      "Mail": false
    },
    {
      "Protocol": "Account_Auth2",
      "ContentLockType": "None",
      "OpenConditionContent": "None",
      "Currency": false,
      "Inventory": false,
      "Mail": false
    },
    {
      "Protocol": "Account_LinkReward",
      "ContentLockType": "None",
      "OpenConditionContent": "None",
      "Currency": false,
      "Inventory": false,
      "Mail": false
    },
    {
      "Protocol": "Account_ReportXignCodeCheater",
      "ContentLockType": "None",
      "OpenConditionContent": "None",
      "Currency": false,
      "Inventory": false,
      "Mail": false
    },
    {
      "Protocol": "Account_DismissRepurchasablePopup",
      "ContentLockType": "None",
      "OpenConditionContent": "None",
      "Currency": false,
      "Inventory": false,
      "Mail": false
    },
    {
      "Protocol": "Account_InvalidateToken",
      "ContentLockType": "None",
      "OpenConditionContent": "None",
      "Currency": false,
      "Inventory": false,
      "Mail": false
    },
    {
      "Protocol": "Account_LoginSync",
      "ContentLockType": "None",
      "OpenConditionContent": "None",
      "Currency": false,
      "Inventory": false,
      "Mail": false
    },
    {
      "Protocol": "Character_List",
      "ContentLockType": "None",
      "OpenConditionContent": "None",
      "Currency": false,
      "Inventory": false,
      "Mail": false
    },
    {
      "Protocol": "Character_Transcendence",
      "ContentLockType": "Unit_Growth_Transcendence",
      "OpenConditionContent": "None",
      "Currency": false,
      "Inventory": false,
      "Mail": false
    },
    {
      "Protocol": "Character_ExpGrowth",
      "ContentLockType": "Unit_Growth_LevelUp",
      "OpenConditionContent": "None",
      "Currency": false,
      "Inventory": false,
      "Mail": false
    },
    {
      "Protocol": "Character_FavorGrowth",
      "ContentLockType": "Favor",
      "OpenConditionContent": "None",
      "Currency": false,
      "Inventory": false,
      "Mail": false
    },
    {
      "Protocol": "Character_UpdateSkillLevel",
      "ContentLockType": "Unit_Growth_Skill",
      "OpenConditionContent": "None",
      "Currency": false,
      "Inventory": false,
      "Mail": false
    },
    {
      "Protocol": "Character_UnlockWeapon",
      "ContentLockType": "None",
      "OpenConditionContent": "None",
      "Currency": false,
      "Inventory": false,
      "Mail": false
    },
    {
      "Protocol": "Character_WeaponExpGrowth",
      "ContentLockType": "None",
      "OpenConditionContent": "None",
      "Currency": false,
      "Inventory": false,
      "Mail": false
    },
    {
      "Protocol": "Character_WeaponTranscendence",
      "ContentLockType": "None",
      "OpenConditionContent": "None",
      "Currency": false,
      "Inventory": false,
      "Mail": false
    },
    {
      "Protocol": "Character_SetFavorites",
      "ContentLockType": "None",
      "OpenConditionContent": "None",
      "Currency": false,
      "Inventory": false,
      "Mail": false
    },
    {
      "Protocol": "Equipment_List",
      "ContentLockType": "None",
      "OpenConditionContent": "None",
      "Currency": false,
      "Inventory": false,
      "Mail": false
    },
    {
      "Protocol": "Equipment_Sell",
      "ContentLockType": "Equipment",
      "OpenConditionContent": "None",
      "Currency": true,
      "Inventory": false,
      "Mail": false
    },
    {
      "Protocol": "Equipment_Equip",
      "ContentLockType": "Equipment",
      "OpenConditionContent": "None",
      "Currency": false,
      "Inventory": false,
      "Mail": false
    },
    {
      "Protocol": "Equipment_LevelUp",
      "ContentLockType": "Equipment",
      "OpenConditionContent": "None",
      "Currency": false,
      "Inventory": false,
      "Mail": false
    },
    {
      "Protocol": "Equipment_TierUp",
      "ContentLockType": "Equipment",
      "OpenConditionContent": "None",
      "Currency": false,
      "Inventory": false,
      "Mail": false
    },
    {
      "Protocol": "Equipment_Lock",
      "ContentLockType": "Equipment",
      "OpenConditionContent": "None",
      "Currency": false,
      "Inventory": false,
      "Mail": false
    },
    {
      "Protocol": "Equipment_BatchGrowth",
      "ContentLockType": "Equipment",
      "OpenConditionContent": "None",
      "Currency": false,
      "Inventory": false,
      "Mail": false
    },
    {
      "Protocol": "Item_List",
      "ContentLockType": "None",
      "OpenConditionContent": "None",
      "Currency": false,
      "Inventory": false,
      "Mail": false
    },
    {
      "Protocol": "Item_Sell",
      "ContentLockType": "Item",
      "OpenConditionContent": "None",
      "Currency": true,
      "Inventory": false,
      "Mail": false
    },
    {
      "Protocol": "Item_Consume",
      "ContentLockType": "Item",
      "OpenConditionContent": "None",
      "Currency": false,
      "Inventory": false,
      "Mail": true
    },
    {
      "Protocol": "Item_Lock",
      "ContentLockType": "Item",
      "OpenConditionContent": "None",
      "Currency": false,
      "Inventory": false,
      "Mail": false
    },
    {
      "Protocol": "Item_BulkConsume",
      "ContentLockType": "Item",
      "OpenConditionContent": "None",
      "Currency": false,
      "Inventory": false,
      "Mail": true
    },
    {
      "Protocol": "Item_SelectTicket",
      "ContentLockType": "Item",
      "OpenConditionContent": "None",
      "Currency": false,
      "Inventory": false,
      "Mail": false
    },
    {
      "Protocol": "Echelon_List",
      "ContentLockType": "None",
      "OpenConditionContent": "None",
      "Currency": false,
      "Inventory": false,
      "Mail": false
    },
    {
      "Protocol": "Echelon_Save",
      "ContentLockType": "Echelon",
      "OpenConditionContent": "None",
      "Currency": false,
      "Inventory": false,
      "Mail": false
    },
    {
      "Protocol": "Campaign_List",
      "ContentLockType": "None",
      "OpenConditionContent": "None",
      "Currency": false,
      "Inventory": false,
      "Mail": false
    },
    {
      "Protocol": "Campaign_EnterMainStage",
      "ContentLockType": "Campaign",
      "OpenConditionContent": "Campaign",
      "Currency": false,
      "Inventory": true,
      "Mail": true
    },
    {
      "Protocol": "Campaign_ConfirmMainStage",
      "ContentLockType": "Campaign",
      "OpenConditionContent": "Campaign",
      "Currency": false,
      "Inventory": true,
      "Mail": true
    },
    {
      "Protocol": "Campaign_DeployEchelon",
      "ContentLockType": "None",
      "OpenConditionContent": "None",
      "Currency": false,
      "Inventory": false,
      "Mail": false
    },
    {
      "Protocol": "Campaign_WithdrawEchelon",
      "ContentLockType": "None",
      "OpenConditionContent": "None",
      "Currency": false,
      "Inventory": false,
      "Mail": false
    },
    {
      "Protocol": "Campaign_MapMove",
      "ContentLockType": "None",
      "OpenConditionContent": "None",
      "Currency": false,
      "Inventory": false,
      "Mail": false
    },
    {
      "Protocol": "Campaign_EndTurn",
      "ContentLockType": "None",
      "OpenConditionContent": "None",
      "Currency": false,
      "Inventory": false,
      "Mail": false
    },
    {
      "Protocol": "Campaign_EnterTactic",
      "ContentLockType": "None",
      "OpenConditionContent": "None",
      "Currency": false,
      "Inventory": false,
      "Mail": false
    },
    {
      "Protocol": "Campaign_TacticResult",
      "ContentLockType": "None",
      "OpenConditionContent": "None",
      "Currency": false,
      "Inventory": false,
      "Mail": false
    },
    {
      "Protocol": "Campaign_Retreat",
      "ContentLockType": "None",
      "OpenConditionContent": "None",
      "Currency": false,
      "Inventory": false,
      "Mail": false
    },
    {
      "Protocol": "Campaign_ChapterClearReward",
      "ContentLockType": "Campaign",
      "OpenConditionContent": "Campaign",
      "Currency": true,
      "Inventory": true,
      "Mail": true
    },
    {
      "Protocol": "Campaign_Heal",
      "ContentLockType": "None",
      "OpenConditionContent": "None",
      "Currency": false,
      "Inventory": false,
      "Mail": false
    },
    {
      "Protocol": "Campaign_EnterSubStage",
      "ContentLockType": "Campaign",
      "OpenConditionContent": "Campaign",
      "Currency": false,
      "Inventory": true,
      "Mail": true
    },
    {
      "Protocol": "Campaign_SubStageResult",
      "ContentLockType": "None",
      "OpenConditionContent": "None",
      "Currency": false,
      "Inventory": false,
      "Mail": false
    },
    {
      "Protocol": "Campaign_Portal",
      "ContentLockType": "None",
      "OpenConditionContent": "None",
      "Currency": false,
      "Inventory": false,
      "Mail": false
    },
    {
      "Protocol": "Campaign_ConfirmTutorialStage",
      "ContentLockType": "None",
      "OpenConditionContent": "None",
      "Currency": false,
      "Inventory": false,
      "Mail": false
    },
    {
      "Protocol": "Campaign_PurchasePlayCountHardStage",
      "ContentLockType": "Campaign",
      "OpenConditionContent": "Campaign",
      "Currency": false,
      "Inventory": false,
      "Mail": false
    },
    {
      "Protocol": "Campaign_EnterTutorialStage",
      "ContentLockType": "None",
      "OpenConditionContent": "None",
      "Currency": false,
      "Inventory": false,
      "Mail": false
    },
    {
      "Protocol": "Campaign_TutorialStageResult",
      "ContentLockType": "None",
      "OpenConditionContent": "None",
      "Currency": false,
      "Inventory": false,
      "Mail": false
    },
    {
      "Protocol": "Campaign_RestartMainStage",
      "ContentLockType": "Campaign",
      "OpenConditionContent": "Campaign",
      "Currency": false,
      "Inventory": false,
      "Mail": false
    },
    {
      "Protocol": "Mail_List",
      "ContentLockType": "None",
      "OpenConditionContent": "None",
      "Currency": false,
      "Inventory": false,
      "Mail": false
    },
    {
      "Protocol": "Mail_Check",
      "ContentLockType": "None",
      "OpenConditionContent": "None",
      "Currency": false,
      "Inventory": false,
      "Mail": false
    },
    {
      "Protocol": "Mail_Receive",
      "ContentLockType": "None",
      "OpenConditionContent": "None",
      "Currency": false,
      "Inventory": false,
      "Mail": false
    },
    {
      "Protocol": "Mission_List",
      "ContentLockType": "None",
      "OpenConditionContent": "None",
      "Currency": false,
      "Inventory": false,
      "Mail": false
    },
    {
      "Protocol": "Mission_Reward",
      "ContentLockType": "NotUseControlledByOtherSetting",
      "OpenConditionContent": "None",
      "Currency": false,
      "Inventory": false,
      "Mail": true
    },
    {
      "Protocol": "Mission_MultipleReward",
      "ContentLockType": "NotUseControlledByOtherSetting",
      "OpenConditionContent": "None",
      "Currency": false,
      "Inventory": false,
      "Mail": true
    },
    {
      "Protocol": "Mission_GuideReward",
      "ContentLockType": "NotUseControlledByOtherSetting",
      "OpenConditionContent": "None",
      "Currency": false,
      "Inventory": false,
      "Mail": true
    },
    {
      "Protocol": "Mission_MultipleGuideReward",
      "ContentLockType": "NotUseControlledByOtherSetting",
      "OpenConditionContent": "None",
      "Currency": false,
      "Inventory": false,
      "Mail": true
    },
    {
      "Protocol": "Mission_Sync",
      "ContentLockType": "None",
      "OpenConditionContent": "None",
      "Currency": false,
      "Inventory": false,
      "Mail": false
    },
    {
      "Protocol": "Attendance_List",
      "ContentLockType": "None",
      "OpenConditionContent": "None",
      "Currency": false,
      "Inventory": false,
      "Mail": false
    },
    {
      "Protocol": "Attendance_Check",
      "ContentLockType": "None",
      "OpenConditionContent": "None",
      "Currency": false,
      "Inventory": false,
      "Mail": false
    },
    {
      "Protocol": "Attendance_Reward",
      "ContentLockType": "None",
      "OpenConditionContent": "None",
      "Currency": false,
      "Inventory": false,
      "Mail": true
    },
    {
      "Protocol": "Shop_BuyMerchandise",
      "ContentLockType": "Shop",
      "OpenConditionContent": "None",
      "Currency": false,
      "Inventory": false,
      "Mail": true
    },
    {
      "Protocol": "Shop_BuyGacha",
      "ContentLockType": "Gacha",
      "OpenConditionContent": "None",
      "Currency": false,
      "Inventory": false,
      "Mail": true
    },
    {
      "Protocol": "Shop_List",
      "ContentLockType": "Shop",
      "OpenConditionContent": "None",
      "Currency": false,
      "Inventory": false,
      "Mail": false
    },
    {
      "Protocol": "Shop_Refresh",
      "ContentLockType": "Shop",
      "OpenConditionContent": "None",
      "Currency": false,
      "Inventory": false,
      "Mail": false
    },
    {
      "Protocol": "Shop_BuyEligma",
      "ContentLockType": "Shop",
      "OpenConditionContent": "None",
      "Currency": false,
      "Inventory": false,
      "Mail": true
    },
    {
      "Protocol": "Shop_BuyGacha2",
      "ContentLockType": "Gacha",
      "OpenConditionContent": "None",
      "Currency": false,
      "Inventory": false,
      "Mail": true
    },
    {
      "Protocol": "Shop_BuyGacha3",
      "ContentLockType": "Gacha",
      "OpenConditionContent": "None",
      "Currency": false,
      "Inventory": false,
      "Mail": true
    },
    {
      "Protocol": "Shop_GachaRecruitList",
      "ContentLockType": "Gacha",
      "OpenConditionContent": "None",
      "Currency": false,
      "Inventory": false,
      "Mail": false
    },
    {
      "Protocol": "Shop_BuyRefreshMerchandise",
      "ContentLockType": "Shop",
      "OpenConditionContent": "None",
      "Currency": false,
      "Inventory": false,
      "Mail": false
    },
    {
      "Protocol": "Shop_BuyAP",
      "ContentLockType": "Shop",
      "OpenConditionContent": "None",
      "Currency": false,
      "Inventory": false,
      "Mail": false
    },
    {
      "Protocol": "Recipe_Craft",
      "ContentLockType": "Craft",
      "OpenConditionContent": "None",
      "Currency": false,
      "Inventory": false,
      "Mail": false
    },
    {
      "Protocol": "MemoryLobby_List",
      "ContentLockType": "None",
      "OpenConditionContent": "None",
      "Currency": false,
      "Inventory": false,
      "Mail": false
    },
    {
      "Protocol": "MemoryLobby_SetMain",
      "ContentLockType": "LobbyIllust",
      "OpenConditionContent": "None",
      "Currency": false,
      "Inventory": false,
      "Mail": false
    },
    {
      "Protocol": "MemoryLobby_UpdateLobbyMode",
      "ContentLockType": "LobbyIllust",
      "OpenConditionContent": "None",
      "Currency": false,
      "Inventory": false,
      "Mail": false
    },
    {
      "Protocol": "MemoryLobby_Interact",
      "ContentLockType": "LobbyIllust",
      "OpenConditionContent": "None",
      "Currency": false,
      "Inventory": false,
      "Mail": false
    },
    {
      "Protocol": "CumulativeTimeReward_List",
      "ContentLockType": "None",
      "OpenConditionContent": "None",
      "Currency": false,
      "Inventory": false,
      "Mail": false
    },
    {
      "Protocol": "CumulativeTimeReward_Reward",
      "ContentLockType": "None",
      "OpenConditionContent": "None",
      "Currency": true,
      "Inventory": true,
      "Mail": true
    },
    {
      "Protocol": "OpenCondition_List",
      "ContentLockType": "None",
      "OpenConditionContent": "None",
      "Currency": false,
      "Inventory": false,
      "Mail": false
    },
    {
      "Protocol": "OpenCondition_EventList",
      "ContentLockType": "None",
      "OpenConditionContent": "None",
      "Currency": false,
      "Inventory": false,
      "Mail": false
    },
    {
      "Protocol": "Toast_List",
      "ContentLockType": "None",
      "OpenConditionContent": "None",
      "Currency": false,
      "Inventory": false,
      "Mail": false
    },
    {
      "Protocol": "Raid_List",
      "ContentLockType": "None",
      "OpenConditionContent": "Shop",
      "Currency": false,
      "Inventory": false,
      "Mail": false
    },
    {
      "Protocol": "Raid_CompleteList",
      "ContentLockType": "None",
      "OpenConditionContent": "Shop",
      "Currency": false,
      "Inventory": false,
      "Mail": false
    },
    {
      "Protocol": "Raid_Detail",
      "ContentLockType": "None",
      "OpenConditionContent": "Shop",
      "Currency": false,
      "Inventory": false,
      "Mail": false
    },
    {
      "Protocol": "Raid_Search",
      "ContentLockType": "None",
      "OpenConditionContent": "Shop",
      "Currency": false,
      "Inventory": false,
      "Mail": false
    },
    {
      "Protocol": "Raid_CreateBattle",
      "ContentLockType": "Raid",
      "OpenConditionContent": "Raid",
      "Currency": true,
      "Inventory": true,
      "Mail": true
    },
    {
      "Protocol": "Raid_EnterBattle",
      "ContentLockType": "Raid",
      "OpenConditionContent": "Raid",
      "Currency": true,
      "Inventory": true,
      "Mail": true
    },
    {
      "Protocol": "Raid_BattleUpdate",
      "ContentLockType": "Raid",
      "OpenConditionContent": "Raid",
      "Currency": false,
      "Inventory": false,
      "Mail": false
    },
    {
      "Protocol": "Raid_EndBattle",
      "ContentLockType": "Raid",
      "OpenConditionContent": "Raid",
      "Currency": false,
      "Inventory": false,
      "Mail": false
    },
    {
      "Protocol": "Raid_Reward",
      "ContentLockType": "Raid",
      "OpenConditionContent": "Raid",
      "Currency": true,
      "Inventory": true,
      "Mail": true
    },
    {
      "Protocol": "Raid_SeasonReward",
      "ContentLockType": "RaidSeasonReward",
      "OpenConditionContent": "Raid",
      "Currency": true,
      "Inventory": true,
      "Mail": true
    },
    {
      "Protocol": "Raid_Lobby",
      "ContentLockType": "None",
      "OpenConditionContent": "None",
      "Currency": false,
      "Inventory": false,
      "Mail": false
    },
    {
      "Protocol": "Raid_GiveUp",
      "ContentLockType": "Raid",
      "OpenConditionContent": "Raid",
      "Currency": false,
      "Inventory": false,
      "Mail": false
    },
    {
      "Protocol": "Raid_OpponentList",
      "ContentLockType": "Raid",
      "OpenConditionContent": "Raid",
      "Currency": false,
      "Inventory": false,
      "Mail": false
    },
    {
      "Protocol": "Raid_RankingReward",
      "ContentLockType": "RaidRankingReward",
      "OpenConditionContent": "Raid",
      "Currency": true,
      "Inventory": true,
      "Mail": true
    },
    {
      "Protocol": "Raid_Login",
      "ContentLockType": "None",
      "OpenConditionContent": "None",
      "Currency": false,
      "Inventory": false,
      "Mail": false
    },
    {
      "Protocol": "Raid_Sweep",
      "ContentLockType": "Raid",
      "OpenConditionContent": "Raid",
      "Currency": true,
      "Inventory": true,
      "Mail": true
    },
    {
      "Protocol": "Raid_GetBestTeam",
      "ContentLockType": "Raid",
      "OpenConditionContent": "Raid",
      "Currency": false,
      "Inventory": false,
      "Mail": false
    },
    {
      "Protocol": "SkipHistory_List",
      "ContentLockType": "None",
      "OpenConditionContent": "None",
      "Currency": false,
      "Inventory": false,
      "Mail": false
    },
    {
      "Protocol": "SkipHistory_Save",
      "ContentLockType": "SkipHistorySave",
      "OpenConditionContent": "None",
      "Currency": false,
      "Inventory": false,
      "Mail": false
    },
    {
      "Protocol": "Scenario_List",
      "ContentLockType": "None",
      "OpenConditionContent": "Shop",
      "Currency": false,
      "Inventory": false,
      "Mail": false
    },
    {
      "Protocol": "Scenario_Clear",
      "ContentLockType": "Story",
      "OpenConditionContent": "Shop",
      "Currency": false,
      "Inventory": false,
      "Mail": false
    },
    {
      "Protocol": "Scenario_GroupHistoryUpdate",
      "ContentLockType": "Story",
      "OpenConditionContent": "Shop",
      "Currency": false,
      "Inventory": false,
      "Mail": false
    },
    {
      "Protocol": "Scenario_Skip",
      "ContentLockType": "Story",
      "OpenConditionContent": "Shop",
      "Currency": false,
      "Inventory": false,
      "Mail": false
    },
    {
      "Protocol": "Scenario_Select",
      "ContentLockType": "Story",
      "OpenConditionContent": "Shop",
      "Currency": false,
      "Inventory": false,
      "Mail": false
    },
    {
      "Protocol": "Scenario_AccountStudentChange",
      "ContentLockType": "None",
      "OpenConditionContent": "Shop",
      "Currency": false,
      "Inventory": false,
      "Mail": false
    },
    {
      "Protocol": "Scenario_LobbyStudentChange",
      "ContentLockType": "LobbyIllust",
      "OpenConditionContent": "Shop",
      "Currency": false,
      "Inventory": false,
      "Mail": false
    },
    {
      "Protocol": "Scenario_SpecialLobbyChange",
      "ContentLockType": "LobbyIllust",
      "OpenConditionContent": "Shop",
      "Currency": false,
      "Inventory": false,
      "Mail": false
    },
    {
      "Protocol": "Scenario_Enter",
      "ContentLockType": "None",
      "OpenConditionContent": "Shop",
      "Currency": false,
      "Inventory": false,
      "Mail": false
    },
    {
      "Protocol": "Cafe_Get",
      "ContentLockType": "None",
      "OpenConditionContent": "None",
      "Currency": false,
      "Inventory": false,
      "Mail": false
    },
    {
      "Protocol": "Cafe_Ack",
      "ContentLockType": "None",
      "OpenConditionContent": "None",
      "Currency": false,
      "Inventory": false,
      "Mail": false
    },
    {
      "Protocol": "Cafe_Deploy",
      "ContentLockType": "Cafe",
      "OpenConditionContent": "Cafe",
      "Currency": false,
      "Inventory": false,
      "Mail": false
    },
    {
      "Protocol": "Cafe_Relocate",
      "ContentLockType": "Cafe",
      "OpenConditionContent": "Cafe",
      "Currency": false,
      "Inventory": false,
      "Mail": false
    },
    {
      "Protocol": "Cafe_Remove",
      "ContentLockType": "Cafe",
      "OpenConditionContent": "Cafe",
      "Currency": false,
      "Inventory": false,
      "Mail": false
    },
    {
      "Protocol": "Cafe_RemoveAll",
      "ContentLockType": "Cafe",
      "OpenConditionContent": "Cafe",
      "Currency": false,
      "Inventory": false,
      "Mail": false
    },
    {
      "Protocol": "Cafe_Interact",
      "ContentLockType": "Cafe",
      "OpenConditionContent": "Cafe",
      "Currency": false,
      "Inventory": false,
      "Mail": false
    },
    {
      "Protocol": "Cafe_ListPreset",
      "ContentLockType": "Cafe",
      "OpenConditionContent": "Cafe",
      "Currency": false,
      "Inventory": false,
      "Mail": false
    },
    {
      "Protocol": "Cafe_RenamePreset",
      "ContentLockType": "Cafe",
      "OpenConditionContent": "Cafe",
      "Currency": false,
      "Inventory": false,
      "Mail": false
    },
    {
      "Protocol": "Cafe_ClearPreset",
      "ContentLockType": "Cafe",
      "OpenConditionContent": "Cafe",
      "Currency": false,
      "Inventory": false,
      "Mail": false
    },
    {
      "Protocol": "Cafe_UpdatePresetFurniture",
      "ContentLockType": "Cafe",
      "OpenConditionContent": "Cafe",
      "Currency": false,
      "Inventory": false,
      "Mail": false
    },
    {
      "Protocol": "Cafe_ApplyPreset",
      "ContentLockType": "Cafe",
      "OpenConditionContent": "Cafe",
      "Currency": false,
      "Inventory": false,
      "Mail": false
    },
    {
      "Protocol": "Cafe_RankUp",
      "ContentLockType": "Cafe",
      "OpenConditionContent": "Cafe",
      "Currency": false,
      "Inventory": false,
      "Mail": false
    },
    {
      "Protocol": "Cafe_ReceiveCurrency",
      "ContentLockType": "Cafe",
      "OpenConditionContent": "Cafe",
      "Currency": true,
      "Inventory": false,
      "Mail": false
    },
    {
      "Protocol": "Cafe_GiveGift",
      "ContentLockType": "Cafe",
      "OpenConditionContent": "Cafe",
      "Currency": false,
      "Inventory": false,
      "Mail": false
    },
    {
      "Protocol": "Cafe_SummonCharacter",
      "ContentLockType": "Cafe",
      "OpenConditionContent": "Cafe_Invite",
      "Currency": false,
      "Inventory": false,
      "Mail": false
    },
    {
      "Protocol": "Cafe_TrophyHistory",
      "ContentLockType": "Cafe",
      "OpenConditionContent": "Cafe",
      "Currency": false,
      "Inventory": false,
      "Mail": false
    },
    {
      "Protocol": "Craft_List",
      "ContentLockType": "None",
      "OpenConditionContent": "None",
      "Currency": false,
      "Inventory": false,
      "Mail": false
    },
    {
      "Protocol": "Craft_SelectNode",
      "ContentLockType": "Craft",
      "OpenConditionContent": "Craft",
      "Currency": false,
      "Inventory": false,
      "Mail": false
    },
    {
      "Protocol": "Craft_UpdateNodeLevel",
      "ContentLockType": "Craft",
      "OpenConditionContent": "Craft",
      "Currency": false,
      "Inventory": false,
      "Mail": false
    },
    {
      "Protocol": "Craft_BeginProcess",
      "ContentLockType": "Craft",
      "OpenConditionContent": "Craft",
      "Currency": false,
      "Inventory": false,
      "Mail": false
    },
    {
      "Protocol": "Craft_CompleteProcess",
      "ContentLockType": "Craft",
      "OpenConditionContent": "Craft",
      "Currency": false,
      "Inventory": false,
      "Mail": false
    },
    {
      "Protocol": "Craft_Reward",
      "ContentLockType": "Craft",
      "OpenConditionContent": "Craft",
      "Currency": false,
      "Inventory": false,
      "Mail": true
    },
    {
      "Protocol": "Craft_HistoryList",
      "ContentLockType": "Craft",
      "OpenConditionContent": "Craft",
      "Currency": false,
      "Inventory": false,
      "Mail": false
    },
    {
      "Protocol": "Craft_ShiftingBeginProcess",
      "ContentLockType": "Craft",
      "OpenConditionContent": "Craft",
      "Currency": false,
      "Inventory": false,
      "Mail": false
    },
    {
      "Protocol": "Craft_ShiftingCompleteProcess",
      "ContentLockType": "Craft",
      "OpenConditionContent": "Craft",
      "Currency": false,
      "Inventory": false,
      "Mail": false
    },
    {
      "Protocol": "Craft_ShiftingReward",
      "ContentLockType": "Craft",
      "OpenConditionContent": "Craft",
      "Currency": false,
      "Inventory": false,
      "Mail": true
    },
    {
      "Protocol": "Arena_EnterLobby",
      "ContentLockType": "Arena",
      "OpenConditionContent": "Arena",
      "Currency": false,
      "Inventory": false,
      "Mail": false
    },
    {
      "Protocol": "Arena_Login",
      "ContentLockType": "None",
      "OpenConditionContent": "None",
      "Currency": false,
      "Inventory": false,
      "Mail": false
    },
    {
      "Protocol": "Arena_SettingChange",
      "ContentLockType": "Arena",
      "OpenConditionContent": "Arena",
      "Currency": false,
      "Inventory": false,
      "Mail": false
    },
    {
      "Protocol": "Arena_OpponentList",
      "ContentLockType": "Arena",
      "OpenConditionContent": "Arena",
      "Currency": false,
      "Inventory": false,
      "Mail": false
    },
    {
      "Protocol": "Arena_EnterBattle",
      "ContentLockType": "Arena",
      "OpenConditionContent": "Arena",
      "Currency": false,
      "Inventory": false,
      "Mail": false
    },
    {
      "Protocol": "Arena_EnterBattlePart1",
      "ContentLockType": "Arena",
      "OpenConditionContent": "Arena",
      "Currency": false,
      "Inventory": true,
      "Mail": true
    },
    {
      "Protocol": "Arena_EnterBattlePart2",
      "ContentLockType": "Arena",
      "OpenConditionContent": "Arena",
      "Currency": false,
      "Inventory": false,
      "Mail": false
    },
    {
      "Protocol": "Arena_BattleResult",
      "ContentLockType": "Arena",
      "OpenConditionContent": "Arena",
      "Currency": false,
      "Inventory": false,
      "Mail": false
    },
    {
      "Protocol": "Arena_CumulativeTimeReward",
      "ContentLockType": "Arena",
      "OpenConditionContent": "Arena",
      "Currency": true,
      "Inventory": true,
      "Mail": true
    },
    {
      "Protocol": "Arena_DailyReward",
      "ContentLockType": "Arena",
      "OpenConditionContent": "Arena",
      "Currency": true,
      "Inventory": true,
      "Mail": true
    },
    {
      "Protocol": "Arena_RankList",
      "ContentLockType": "Arena",
      "OpenConditionContent": "Arena",
      "Currency": false,
      "Inventory": false,
      "Mail": false
    },
    {
      "Protocol": "Arena_History",
      "ContentLockType": "Arena",
      "OpenConditionContent": "Arena",
      "Currency": false,
      "Inventory": false,
      "Mail": false
    },
    {
      "Protocol": "Arena_RecordSync",
      "ContentLockType": "Arena",
      "OpenConditionContent": "Arena",
      "Currency": false,
      "Inventory": false,
      "Mail": false
    },
    {
      "Protocol": "Arena_TicketPurchase",
      "ContentLockType": "Arena",
      "OpenConditionContent": "Arena",
      "Currency": false,
      "Inventory": false,
      "Mail": false
    },
    {
      "Protocol": "Arena_DamageReport",
      "ContentLockType": "Arena",
      "OpenConditionContent": "Arena",
      "Currency": false,
      "Inventory": false,
      "Mail": false
    },
    {
      "Protocol": "Arena_CheckSeasonCloseReward",
      "ContentLockType": "Arena",
      "OpenConditionContent": "Arena",
      "Currency": false,
      "Inventory": false,
      "Mail": false
    },
    {
      "Protocol": "Arena_SyncEchelonSettingTime",
      "ContentLockType": "Arena",
      "OpenConditionContent": "Arena",
      "Currency": false,
      "Inventory": false,
      "Mail": true
    },
    {
      "Protocol": "WeekDungeon_List",
      "ContentLockType": "None",
      "OpenConditionContent": "None",
      "Currency": false,
      "Inventory": false,
      "Mail": false
    },
    {
      "Protocol": "WeekDungeon_EnterBattle",
      "ContentLockType": "NotUseControlledByOtherSetting",
      "OpenConditionContent": "None",
      "Currency": false,
      "Inventory": true,
      "Mail": true
    },
    {
      "Protocol": "WeekDungeon_BattleResult",
      "ContentLockType": "NotUseControlledByOtherSetting",
      "OpenConditionContent": "None",
      "Currency": false,
      "Inventory": false,
      "Mail": false
    },
    {
      "Protocol": "WeekDungeon_Retreat",
      "ContentLockType": "NotUseControlledByOtherSetting",
      "OpenConditionContent": "None",
      "Currency": false,
      "Inventory": false,
      "Mail": false
    },
    {
      "Protocol": "Academy_GetInfo",
      "ContentLockType": "None",
      "OpenConditionContent": "None",
      "Currency": false,
      "Inventory": false,
      "Mail": false
    },
    {
      "Protocol": "Academy_AttendSchedule",
      "ContentLockType": "NotUseControlledByOtherSetting",
      "OpenConditionContent": "Academy",
      "Currency": false,
      "Inventory": true,
      "Mail": true
    },
    {
      "Protocol": "Event_GetList",
      "ContentLockType": "None",
      "OpenConditionContent": "None",
      "Currency": false,
      "Inventory": false,
      "Mail": false
    },
    {
      "Protocol": "Event_GetImage",
      "ContentLockType": "None",
      "OpenConditionContent": "None",
      "Currency": false,
      "Inventory": false,
      "Mail": false
    },
    {
      "Protocol": "Event_UseCoupon",
      "ContentLockType": "None",
      "OpenConditionContent": "None",
      "Currency": false,
      "Inventory": false,
      "Mail": false
    },
    {
      "Protocol": "Event_RewardIncrease",
      "ContentLockType": "None",
      "OpenConditionContent": "None",
      "Currency": false,
      "Inventory": false,
      "Mail": false
    },
    {
      "Protocol": "ContentSave_Get",
      "ContentLockType": "None",
      "OpenConditionContent": "None",
      "Currency": false,
      "Inventory": false,
      "Mail": false
    },
    {
      "Protocol": "ContentSave_Discard",
      "ContentLockType": "None",
      "OpenConditionContent": "None",
      "Currency": false,
      "Inventory": false,
      "Mail": false
    },
    {
      "Protocol": "ContentSweep_Request",
      "ContentLockType": "NotUseControlledByOtherSetting",
      "OpenConditionContent": "None",
      "Currency": false,
      "Inventory": true,
      "Mail": true
    },
    {
      "Protocol": "Clan_Lobby",
      "ContentLockType": "Clan",
      "OpenConditionContent": "Clan",
      "Currency": false,
      "Inventory": false,
      "Mail": false
    },
    {
      "Protocol": "Clan_Login",
      "ContentLockType": "None",
      "OpenConditionContent": "None",
      "Currency": false,
      "Inventory": false,
      "Mail": false
    },
    {
      "Protocol": "Clan_Search",
      "ContentLockType": "Clan",
      "OpenConditionContent": "Clan",
      "Currency": false,
      "Inventory": false,
      "Mail": false
    },
    {
      "Protocol": "Clan_Create",
      "ContentLockType": "Clan",
      "OpenConditionContent": "Clan",
      "Currency": false,
      "Inventory": false,
      "Mail": false
    },
    {
      "Protocol": "Clan_Member",
      "ContentLockType": "Clan",
      "OpenConditionContent": "Clan",
      "Currency": false,
      "Inventory": false,
      "Mail": false
    },
    {
      "Protocol": "Clan_Applicant",
      "ContentLockType": "Clan",
      "OpenConditionContent": "Clan",
      "Currency": false,
      "Inventory": false,
      "Mail": false
    },
    {
      "Protocol": "Clan_Join",
      "ContentLockType": "Clan",
      "OpenConditionContent": "Clan",
      "Currency": false,
      "Inventory": false,
      "Mail": false
    },
    {
      "Protocol": "Clan_Quit",
      "ContentLockType": "Clan",
      "OpenConditionContent": "Clan",
      "Currency": false,
      "Inventory": false,
      "Mail": false
    },
    {
      "Protocol": "Clan_Permit",
      "ContentLockType": "Clan",
      "OpenConditionContent": "Clan",
      "Currency": false,
      "Inventory": false,
      "Mail": false
    },
    {
      "Protocol": "Clan_Kick",
      "ContentLockType": "Clan",
      "OpenConditionContent": "Clan",
      "Currency": false,
      "Inventory": false,
      "Mail": false
    },
    {
      "Protocol": "Clan_Setting",
      "ContentLockType": "Clan",
      "OpenConditionContent": "Clan",
      "Currency": false,
      "Inventory": false,
      "Mail": false
    },
    {
      "Protocol": "Clan_Confer",
      "ContentLockType": "Clan",
      "OpenConditionContent": "Clan",
      "Currency": false,
      "Inventory": false,
      "Mail": false
    },
    {
      "Protocol": "Clan_Dismiss",
      "ContentLockType": "Clan",
      "OpenConditionContent": "Clan",
      "Currency": false,
      "Inventory": false,
      "Mail": false
    },
    {
      "Protocol": "Clan_AutoJoin",
      "ContentLockType": "Clan",
      "OpenConditionContent": "Clan",
      "Currency": false,
      "Inventory": false,
      "Mail": false
    },
    {
      "Protocol": "Clan_MemberList",
      "ContentLockType": "Clan",
      "OpenConditionContent": "Clan",
      "Currency": false,
      "Inventory": false,
      "Mail": false
    },
    {
      "Protocol": "Clan_CancelApply",
      "ContentLockType": "Clan",
      "OpenConditionContent": "Clan",
      "Currency": false,
      "Inventory": false,
      "Mail": false
    },
    {
      "Protocol": "Clan_AssistList",
      "ContentLockType": "Clan",
      "OpenConditionContent": "Clan",
      "Currency": false,
      "Inventory": false,
      "Mail": false
    },
    {
      "Protocol": "Clan_SetAssist",
      "ContentLockType": "Clan",
      "OpenConditionContent": "Clan",
      "Currency": false,
      "Inventory": false,
      "Mail": false
    },
    {
      "Protocol": "Clan_ReceiveTermReward",
      "ContentLockType": "Clan",
      "OpenConditionContent": "Clan",
      "Currency": true,
      "Inventory": true,
      "Mail": true
    },
    {
      "Protocol": "Clan_ReceiveRentReward",
      "ContentLockType": "Clan",
      "OpenConditionContent": "Clan",
      "Currency": true,
      "Inventory": true,
      "Mail": true
    },
    {
      "Protocol": "Clan_ChatLog",
      "ContentLockType": "Clan",
      "OpenConditionContent": "Clan",
      "Currency": false,
      "Inventory": false,
      "Mail": false
    },
    {
      "Protocol": "Clan_Check",
      "ContentLockType": "None",
      "OpenConditionContent": "None",
      "Currency": false,
      "Inventory": false,
      "Mail": false
    },
    {
      "Protocol": "Clan_AllAssistList",
      "ContentLockType": "None",
      "OpenConditionContent": "None",
      "Currency": false,
      "Inventory": false,
      "Mail": false
    },
    {
      "Protocol": "Billing_TransactionStartByYostar",
      "ContentLockType": "None",
      "OpenConditionContent": "None",
      "Currency": false,
      "Inventory": false,
      "Mail": false
    },
    {
      "Protocol": "Billing_TransactionEndByYostar",
      "ContentLockType": "Billing",
      "OpenConditionContent": "Billing",
      "Currency": false,
      "Inventory": false,
      "Mail": false
    },
    {
      "Protocol": "Billing_PurchaseListByYostar",
      "ContentLockType": "Billing",
      "OpenConditionContent": "Billing",
      "Currency": false,
      "Inventory": false,
      "Mail": false
    },
    {
      "Protocol": "EventContent_AdventureList",
      "ContentLockType": "NotUseControlledByOtherSetting",
      "OpenConditionContent": "EventContent",
      "Currency": false,
      "Inventory": false,
      "Mail": false
    },
    {
      "Protocol": "EventContent_EnterMainStage",
      "ContentLockType": "NotUseControlledByOtherSetting",
      "OpenConditionContent": "EventContent",
      "Currency": false,
      "Inventory": true,
      "Mail": true
    },
    {
      "Protocol": "EventContent_ConfirmMainStage",
      "ContentLockType": "NotUseControlledByOtherSetting",
      "OpenConditionContent": "EventContent",
      "Currency": false,
      "Inventory": true,
      "Mail": true
    },
    {
      "Protocol": "EventContent_EnterTactic",
      "ContentLockType": "NotUseControlledByOtherSetting",
      "OpenConditionContent": "None",
      "Currency": false,
      "Inventory": false,
      "Mail": false
    },
    {
      "Protocol": "EventContent_TacticResult",
      "ContentLockType": "NotUseControlledByOtherSetting",
      "OpenConditionContent": "None",
      "Currency": false,
      "Inventory": false,
      "Mail": false
    },
    {
      "Protocol": "EventContent_EnterSubStage",
      "ContentLockType": "NotUseControlledByOtherSetting",
      "OpenConditionContent": "EventContent",
      "Currency": false,
      "Inventory": true,
      "Mail": true
    },
    {
      "Protocol": "EventContent_SubStageResult",
      "ContentLockType": "NotUseControlledByOtherSetting",
      "OpenConditionContent": "None",
      "Currency": false,
      "Inventory": false,
      "Mail": false
    },
    {
      "Protocol": "EventContent_DeployEchelon",
      "ContentLockType": "NotUseControlledByOtherSetting",
      "OpenConditionContent": "None",
      "Currency": false,
      "Inventory": false,
      "Mail": false
    },
    {
      "Protocol": "EventContent_WithdrawEchelon",
      "ContentLockType": "NotUseControlledByOtherSetting",
      "OpenConditionContent": "None",
      "Currency": false,
      "Inventory": false,
      "Mail": false
    },
    {
      "Protocol": "EventContent_MapMove",
      "ContentLockType": "NotUseControlledByOtherSetting",
      "OpenConditionContent": "None",
      "Currency": false,
      "Inventory": false,
      "Mail": false
    },
    {
      "Protocol": "EventContent_EndTurn",
      "ContentLockType": "NotUseControlledByOtherSetting",
      "OpenConditionContent": "None",
      "Currency": false,
      "Inventory": false,
      "Mail": false
    },
    {
      "Protocol": "EventContent_Retreat",
      "ContentLockType": "NotUseControlledByOtherSetting",
      "OpenConditionContent": "None",
      "Currency": false,
      "Inventory": false,
      "Mail": false
    },
    {
      "Protocol": "EventContent_Portal",
      "ContentLockType": "NotUseControlledByOtherSetting",
      "OpenConditionContent": "None",
      "Currency": false,
      "Inventory": false,
      "Mail": false
    },
    {
      "Protocol": "EventContent_PurchasePlayCountHardStage",
      "ContentLockType": "NotUseControlledByOtherSetting",
      "OpenConditionContent": "EventContent",
      "Currency": false,
      "Inventory": false,
      "Mail": false
    },
    {
      "Protocol": "EventContent_ShopList",
      "ContentLockType": "NotUseControlledByOtherSetting",
      "OpenConditionContent": "EventContent",
      "Currency": false,
      "Inventory": false,
      "Mail": false
    },
    {
      "Protocol": "EventContent_ShopRefresh",
      "ContentLockType": "NotUseControlledByOtherSetting",
      "OpenConditionContent": "EventContent",
      "Currency": false,
      "Inventory": false,
      "Mail": false
    },
    {
      "Protocol": "EventContent_ReceiveStageTotalReward",
      "ContentLockType": "NotUseControlledByOtherSetting",
      "OpenConditionContent": "EventContent",
      "Currency": true,
      "Inventory": true,
      "Mail": true
    },
    {
      "Protocol": "EventContent_EnterMainGroundStage",
      "ContentLockType": "NotUseControlledByOtherSetting",
      "OpenConditionContent": "EventContent",
      "Currency": false,
      "Inventory": true,
      "Mail": true
    },
    {
      "Protocol": "EventContent_MainGroundStageResult",
      "ContentLockType": "NotUseControlledByOtherSetting",
      "OpenConditionContent": "None",
      "Currency": false,
      "Inventory": false,
      "Mail": false
    },
    {
      "Protocol": "EventContent_ShopBuyMerchandise",
      "ContentLockType": "NotUseControlledByOtherSetting",
      "OpenConditionContent": "Shop",
      "Currency": false,
      "Inventory": false,
      "Mail": true
    },
    {
      "Protocol": "EventContent_BoxGachaShopList",
      "ContentLockType": "NotUseControlledByOtherSetting",
      "OpenConditionContent": "EventContent",
      "Currency": false,
      "Inventory": false,
      "Mail": false
    },
    {
      "Protocol": "EventContent_BoxGachaShopPurchase",
      "ContentLockType": "NotUseControlledByOtherSetting",
      "OpenConditionContent": "EventContent",
      "Currency": false,
      "Inventory": false,
      "Mail": true
    },
    {
      "Protocol": "EventContent_BoxGachaShopRefresh",
      "ContentLockType": "NotUseControlledByOtherSetting",
      "OpenConditionContent": "EventContent",
      "Currency": false,
      "Inventory": false,
      "Mail": false
    },
    {
      "Protocol": "EventContent_CollectionList",
      "ContentLockType": "NotUseControlledByOtherSetting",
      "OpenConditionContent": "None",
      "Currency": false,
      "Inventory": false,
      "Mail": false
    },
    {
      "Protocol": "EventContent_CollectionForMission",
      "ContentLockType": "NotUseControlledByOtherSetting",
      "OpenConditionContent": "None",
      "Currency": false,
      "Inventory": false,
      "Mail": false
    },
    {
      "Protocol": "EventContent_EnterStoryStage",
      "ContentLockType": "NotUseControlledByOtherSetting",
      "OpenConditionContent": "EventContent",
      "Currency": false,
      "Inventory": false,
      "Mail": false
    },
    {
      "Protocol": "EventContent_StoryStageResult",
      "ContentLockType": "NotUseControlledByOtherSetting",
      "OpenConditionContent": "EventContent",
      "Currency": false,
      "Inventory": false,
      "Mail": false
    },
    {
      "Protocol": "EventContent_DiceRaceLobby",
      "ContentLockType": "NotUseControlledByOtherSetting",
      "OpenConditionContent": "EventContent",
      "Currency": false,
      "Inventory": false,
      "Mail": false
    },
    {
      "Protocol": "EventContent_DiceRaceRoll",
      "ContentLockType": "NotUseControlledByOtherSetting",
      "OpenConditionContent": "EventContent",
      "Currency": true,
      "Inventory": false,
      "Mail": true
    },
    {
      "Protocol": "EventContent_DiceRaceLapReward",
      "ContentLockType": "NotUseControlledByOtherSetting",
      "OpenConditionContent": "EventContent",
      "Currency": true,
      "Inventory": true,
      "Mail": true
    },
    {
      "Protocol": "TTS_GetFile",
      "ContentLockType": "None",
      "OpenConditionContent": "None",
      "Currency": false,
      "Inventory": false,
      "Mail": false
    },
    {
      "Protocol": "ContentLog_UIOpenStatistics",
      "ContentLockType": "None",
      "OpenConditionContent": "None",
      "Currency": false,
      "Inventory": false,
      "Mail": false
    },
    {
      "Protocol": "MomoTalk_OutLine",
      "ContentLockType": "None",
      "OpenConditionContent": "None",
      "Currency": false,
      "Inventory": false,
      "Mail": false
    },
    {
      "Protocol": "MomoTalk_MessageList",
      "ContentLockType": "MomoTalk",
      "OpenConditionContent": "None",
      "Currency": false,
      "Inventory": false,
      "Mail": false
    },
    {
      "Protocol": "MomoTalk_Read",
      "ContentLockType": "MomoTalk",
      "OpenConditionContent": "None",
      "Currency": false,
      "Inventory": false,
      "Mail": false
    },
    {
      "Protocol": "MomoTalk_FavorSchedule",
      "ContentLockType": "MomoTalk",
      "OpenConditionContent": "None",
      "Currency": false,
      "Inventory": false,
      "Mail": false
    },
    {
      "Protocol": "ClearDeck_List",
      "ContentLockType": "None",
      "OpenConditionContent": "None",
      "Currency": false,
      "Inventory": false,
      "Mail": false
    },
    {
      "Protocol": "Queuing_GetTicket",
      "ContentLockType": "None",
      "OpenConditionContent": "None",
      "Currency": false,
      "Inventory": false,
      "Mail": false
    },
    {
      "Protocol": "MiniGame_StageList",
      "ContentLockType": "NotUseControlledByOtherSetting",
      "OpenConditionContent": "EventContent",
      "Currency": false,
      "Inventory": false,
      "Mail": false
    },
    {
      "Protocol": "MiniGame_EnterStage",
      "ContentLockType": "NotUseControlledByOtherSetting",
      "OpenConditionContent": "EventContent",
      "Currency": false,
      "Inventory": false,
      "Mail": false
    },
    {
      "Protocol": "MiniGame_Result",
      "ContentLockType": "NotUseControlledByOtherSetting",
      "OpenConditionContent": "EventContent",
      "Currency": false,
      "Inventory": false,
      "Mail": false
    },
    {
      "Protocol": "MiniGame_MissionList",
      "ContentLockType": "None",
      "OpenConditionContent": "None",
      "Currency": false,
      "Inventory": false,
      "Mail": false
    },
    {
      "Protocol": "MiniGame_MissionReward",
      "ContentLockType": "NotUseControlledByOtherSetting",
      "OpenConditionContent": "EventContent",
      "Currency": false,
      "Inventory": false,
      "Mail": true
    },
    {
      "Protocol": "MiniGame_MissionMultipleReward",
      "ContentLockType": "NotUseControlledByOtherSetting",
      "OpenConditionContent": "EventContent",
      "Currency": false,
      "Inventory": false,
      "Mail": true
    },
    {
      "Protocol": "Notification_LobbyCheck",
      "ContentLockType": "None",
      "OpenConditionContent": "None",
      "Currency": false,
      "Inventory": false,
      "Mail": false
    },
    {
      "Protocol": "Notification_EventContentReddotCheck",
      "ContentLockType": "None",
      "OpenConditionContent": "None",
      "Currency": false,
      "Inventory": false,
      "Mail": false
    },
    {
      "Protocol": "SchoolDungeon_List",
      "ContentLockType": "SchoolDungeon",
      "OpenConditionContent": "SchoolDungeon",
      "Currency": false,
      "Inventory": false,
      "Mail": false
    },
    {
      "Protocol": "SchoolDungeon_EnterBattle",
      "ContentLockType": "SchoolDungeon",
      "OpenConditionContent": "SchoolDungeon",
      "Currency": false,
      "Inventory": true,
      "Mail": true
    },
    {
      "Protocol": "SchoolDungeon_BattleResult",
      "ContentLockType": "SchoolDungeon",
      "OpenConditionContent": "SchoolDungeon",
      "Currency": false,
      "Inventory": false,
      "Mail": false
    },
    {
      "Protocol": "SchoolDungeon_Retreat",
      "ContentLockType": "SchoolDungeon",
      "OpenConditionContent": "SchoolDungeon",
      "Currency": false,
      "Inventory": false,
      "Mail": false
    },
    {
      "Protocol": "TimeAttackDungeon_Lobby",
      "ContentLockType": "TimeAttackDungeon",
      "OpenConditionContent": "TimeAttackDungeon",
      "Currency": false,
      "Inventory": false,
      "Mail": false
    },
    {
      "Protocol": "TimeAttackDungeon_CreateBattle",
      "ContentLockType": "TimeAttackDungeon",
      "OpenConditionContent": "TimeAttackDungeon",
      "Currency": false,
      "Inventory": true,
      "Mail": true
    },
    {
      "Protocol": "TimeAttackDungeon_EnterBattle",
      "ContentLockType": "TimeAttackDungeon",
      "OpenConditionContent": "TimeAttackDungeon",
      "Currency": false,
      "Inventory": true,
      "Mail": true
    },
    {
      "Protocol": "TimeAttackDungeon_EndBattle",
      "ContentLockType": "TimeAttackDungeon",
      "OpenConditionContent": "TimeAttackDungeon",
      "Currency": false,
      "Inventory": false,
      "Mail": false
    },
    {
      "Protocol": "TimeAttackDungeon_Sweep",
      "ContentLockType": "TimeAttackDungeon",
      "OpenConditionContent": "TimeAttackDungeon",
      "Currency": true,
      "Inventory": true,
      "Mail": true
    },
    {
      "Protocol": "TimeAttackDungeon_GiveUp",
      "ContentLockType": "TimeAttackDungeon",
      "OpenConditionContent": "TimeAttackDungeon",
      "Currency": false,
      "Inventory": false,
      "Mail": false
    },
    {
      "Protocol": "TimeAttackDungeon_Login",
      "ContentLockType": "None",
      "OpenConditionContent": "None",
      "Currency": false,
      "Inventory": false,
      "Mail": false
    },
    {
      "Protocol": "WorldRaid_Lobby",
      "ContentLockType": "NotUseControlledByOtherSetting",
      "OpenConditionContent": "EventContent",
      "Currency": false,
      "Inventory": false,
      "Mail": false
    },
    {
      "Protocol": "WorldRaid_BossList",
      "ContentLockType": "NotUseControlledByOtherSetting",
      "OpenConditionContent": "EventContent",
      "Currency": false,
      "Inventory": false,
      "Mail": false
    },
    {
      "Protocol": "WorldRaid_EnterBattle",
      "ContentLockType": "NotUseControlledByOtherSetting",
      "OpenConditionContent": "EventContent",
      "Currency": true,
      "Inventory": true,
      "Mail": true
    },
    {
      "Protocol": "WorldRaid_BattleResult",
      "ContentLockType": "NotUseControlledByOtherSetting",
      "OpenConditionContent": "EventContent",
      "Currency": false,
      "Inventory": false,
      "Mail": false
    },
    {
      "Protocol": "WorldRaid_ReceiveReward",
      "ContentLockType": "NotUseControlledByOtherSetting",
      "OpenConditionContent": "EventContent",
      "Currency": true,
      "Inventory": true,
      "Mail": true
    },
    {
      "Protocol": "Conquest_GetInfo",
      "ContentLockType": "NotUseControlledByOtherSetting",
      "OpenConditionContent": "EventContent",
      "Currency": false,
      "Inventory": false,
      "Mail": false
    },
    {
      "Protocol": "Conquest_Conquer",
      "ContentLockType": "NotUseControlledByOtherSetting",
      "OpenConditionContent": "EventContent",
      "Currency": false,
      "Inventory": false,
      "Mail": true
    },
    {
      "Protocol": "Conquest_ConquerWithBattleStart",
      "ContentLockType": "NotUseControlledByOtherSetting",
      "OpenConditionContent": "EventContent",
      "Currency": false,
      "Inventory": false,
      "Mail": false
    },
    {
      "Protocol": "Conquest_ConquerWithBattleResult",
      "ContentLockType": "NotUseControlledByOtherSetting",
      "OpenConditionContent": "EventContent",
      "Currency": false,
      "Inventory": false,
      "Mail": true
    },
    {
      "Protocol": "Conquest_DeployEchelon",
      "ContentLockType": "NotUseControlledByOtherSetting",
      "OpenConditionContent": "EventContent",
      "Currency": false,
      "Inventory": false,
      "Mail": false
    },
    {
      "Protocol": "Conquest_ManageBase",
      "ContentLockType": "NotUseControlledByOtherSetting",
      "OpenConditionContent": "EventContent",
      "Currency": false,
      "Inventory": false,
      "Mail": true
    },
    {
      "Protocol": "Conquest_UpgradeBase",
      "ContentLockType": "NotUseControlledByOtherSetting",
      "OpenConditionContent": "EventContent",
      "Currency": false,
      "Inventory": false,
      "Mail": false
    },
    {
      "Protocol": "Conquest_TakeEventObject",
      "ContentLockType": "NotUseControlledByOtherSetting",
      "OpenConditionContent": "EventContent",
      "Currency": false,
      "Inventory": false,
      "Mail": true
    },
    {
      "Protocol": "Conquest_EventObjectBattleStart",
      "ContentLockType": "NotUseControlledByOtherSetting",
      "OpenConditionContent": "EventContent",
      "Currency": false,
      "Inventory": false,
      "Mail": false
    },
    {
      "Protocol": "Conquest_EventObjectBattleResult",
      "ContentLockType": "NotUseControlledByOtherSetting",
      "OpenConditionContent": "EventContent",
      "Currency": false,
      "Inventory": false,
      "Mail": true
    },
    {
      "Protocol": "Conquest_ReceiveCalculateRewards",
      "ContentLockType": "NotUseControlledByOtherSetting",
      "OpenConditionContent": "EventContent",
      "Currency": false,
      "Inventory": false,
      "Mail": true
    },
    {
      "Protocol": "Conquest_NormalizeEchelon",
      "ContentLockType": "NotUseControlledByOtherSetting",
      "OpenConditionContent": "EventContent",
      "Currency": false,
      "Inventory": false,
      "Mail": false
    },
    {
      "Protocol": "Conquest_Check",
      "ContentLockType": "NotUseControlledByOtherSetting",
      "OpenConditionContent": "EventContent",
      "Currency": false,
      "Inventory": false,
      "Mail": false
    },
    {
      "Protocol": "Friend_List",
      "ContentLockType": "Friend",
      "OpenConditionContent": "None",
      "Currency": false,
      "Inventory": false,
      "Mail": false
    },
    {
      "Protocol": "Friend_Remove",
      "ContentLockType": "Friend",
      "OpenConditionContent": "None",
      "Currency": false,
      "Inventory": false,
      "Mail": false
    },
    {
      "Protocol": "Friend_GetFriendDetailedInfo",
      "ContentLockType": "Friend",
      "OpenConditionContent": "None",
      "Currency": false,
      "Inventory": false,
      "Mail": false
    },
    {
      "Protocol": "Friend_GetIdCard",
      "ContentLockType": "Friend",
      "OpenConditionContent": "None",
      "Currency": false,
      "Inventory": false,
      "Mail": false
    },
    {
      "Protocol": "Friend_SetIdCard",
      "ContentLockType": "Friend",
      "OpenConditionContent": "None",
      "Currency": false,
      "Inventory": false,
      "Mail": false
    },
    {
      "Protocol": "Friend_Search",
      "ContentLockType": "Friend",
      "OpenConditionContent": "None",
      "Currency": false,
      "Inventory": false,
      "Mail": false
    },
    {
      "Protocol": "Friend_SendFriendRequest",
      "ContentLockType": "Friend",
      "OpenConditionContent": "None",
      "Currency": false,
      "Inventory": false,
      "Mail": false
    },
    {
      "Protocol": "Friend_AcceptFriendRequest",
      "ContentLockType": "Friend",
      "OpenConditionContent": "None",
      "Currency": false,
      "Inventory": false,
      "Mail": false
    },
    {
      "Protocol": "Friend_DeclineFriendRequest",
      "ContentLockType": "Friend",
      "OpenConditionContent": "None",
      "Currency": false,
      "Inventory": false,
      "Mail": false
    },
    {
      "Protocol": "Friend_CancelFriendRequest",
      "ContentLockType": "Friend",
      "OpenConditionContent": "None",
      "Currency": false,
      "Inventory": false,
      "Mail": false
    },
    {
      "Protocol": "Friend_Check",
      "ContentLockType": "Friend",
      "OpenConditionContent": "None",
      "Currency": false,
      "Inventory": false,
      "Mail": false
    },
    {
      "Protocol": "CharacterGear_List",
      "ContentLockType": "Equipment",
      "OpenConditionContent": "None",
      "Currency": false,
      "Inventory": false,
      "Mail": false
    },
    {
      "Protocol": "CharacterGear_Unlock",
      "ContentLockType": "Equipment",
      "OpenConditionContent": "None",
      "Currency": false,
      "Inventory": false,
      "Mail": false
    },
    {
      "Protocol": "CharacterGear_TierUp",
      "ContentLockType": "Equipment",
      "OpenConditionContent": "None",
      "Currency": false,
      "Inventory": false,
      "Mail": false
    }
  ]
}
